deromanize/__init__.py
deromanize/cacheutils.py
deromanize/config.py
deromanize/keygenerator.py
deromanize/tools.py
deromanize/trees.py
deromanize-0.9.dist-info/METADATA
deromanize-0.9.dist-info/WHEEL
deromanize-0.9.dist-info/top_level.txt
deromanize-0.9.dist-info/RECORD
