Metadata-Version: 2.1
Name: deromanize
Version: 0.9
Summary: rule-based algorithms converting Romanized text to original scripts
Home-page: https://github.com/FID-Judaica/deromanize.py
Author: FID-Judaica, Goethe Universität
Author-email: a.christianson@ub.uni-frankfurt.de
License: MLP 2.0/EUPL 1.1
Platform: UNKNOWN
Requires: libaaron
Requires: pyyaml
Requires: sqlalchemy
